README.md
setup.py
vidrl_hiv.egg-info/PKG-INFO
vidrl_hiv.egg-info/SOURCES.txt
vidrl_hiv.egg-info/dependency_links.txt
vidrl_hiv.egg-info/entry_points.txt
vidrl_hiv.egg-info/requires.txt
vidrl_hiv.egg-info/top_level.txt
vidrlhiv/__init__.py
vidrlhiv/files_to_input.py
vidrlhiv/hiv.py
vidrlhiv/dirty_pipeline_ammar/conda.yaml
vidrlhiv/dirty_pipeline_ammar/snakefile
vidrlhiv/dirty_pipeline_ammar/resources/depth.totals.csv
vidrlhiv/dirty_pipeline_ammar/resources/drm.bed
vidrlhiv/dirty_pipeline_ammar/resources/drm1.tsv
vidrlhiv/dirty_pipeline_ammar/resources/genes.bed
vidrlhiv/dirty_pipeline_ammar/resources/references/01_AE.fasta
vidrlhiv/dirty_pipeline_ammar/resources/references/02_AG.fasta
vidrlhiv/dirty_pipeline_ammar/resources/references/03_A6B.fasta
vidrlhiv/dirty_pipeline_ammar/resources/references/04_cpx.fasta
vidrlhiv/dirty_pipeline_ammar/resources/references/05_DF.fasta
vidrlhiv/dirty_pipeline_ammar/resources/references/06_cpx.fasta
vidrlhiv/dirty_pipeline_ammar/resources/references/07_BC.fasta
vidrlhiv/dirty_pipeline_ammar/resources/references/08_BC.fasta
vidrlhiv/dirty_pipeline_ammar/resources/references/09_cpx.fasta
vidrlhiv/dirty_pipeline_ammar/resources/references/100_01C.fasta
vidrlhiv/dirty_pipeline_ammar/resources/references/101_01B.fasta
vidrlhiv/dirty_pipeline_ammar/resources/references/102_0107.fasta
vidrlhiv/dirty_pipeline_ammar/resources/references/103_01B.fasta
vidrlhiv/dirty_pipeline_ammar/resources/references/104_0107.fasta
vidrlhiv/dirty_pipeline_ammar/resources/references/105_0108.fasta
vidrlhiv/dirty_pipeline_ammar/resources/references/106_cpx.fasta
vidrlhiv/dirty_pipeline_ammar/resources/references/107_01B.fasta
vidrlhiv/dirty_pipeline_ammar/resources/references/108_BC.fasta
vidrlhiv/dirty_pipeline_ammar/resources/references/109_0107.fasta
vidrlhiv/dirty_pipeline_ammar/resources/references/10_CD.fasta
vidrlhiv/dirty_pipeline_ammar/resources/references/110_BC.fasta
vidrlhiv/dirty_pipeline_ammar/resources/references/111_01C.fasta
vidrlhiv/dirty_pipeline_ammar/resources/references/112_01B.fasta
vidrlhiv/dirty_pipeline_ammar/resources/references/113_0107.fasta
vidrlhiv/dirty_pipeline_ammar/resources/references/114_0155.fasta
