Metadata-Version: 2.4
Name: vidrl-hiv
Version: 0.1.4
Summary: project_description
Home-page: https://github.com/abcdtree/vidrl-hiv
Author: Josh Zhang and Ammar Aziz
Requires-Dist: snakemake>=9.0
Requires-Dist: pandas
Dynamic: author
Dynamic: description
Dynamic: description-content-type
Dynamic: home-page
Dynamic: requires-dist
Dynamic: summary
